ionoscloud_dbaas_mongo/__init__.py
ionoscloud_dbaas_mongo/api_client.py
ionoscloud_dbaas_mongo/configuration.py
ionoscloud_dbaas_mongo/exceptions.py
ionoscloud_dbaas_mongo/rest.py
ionoscloud_dbaas_mongo/test-driver.py
ionoscloud_dbaas_mongo/api/__init__.py
ionoscloud_dbaas_mongo/api/clusters_api.py
ionoscloud_dbaas_mongo/api/logs_api.py
ionoscloud_dbaas_mongo/api/metadata_api.py
ionoscloud_dbaas_mongo/api/restores_api.py
ionoscloud_dbaas_mongo/api/snapshots_api.py
ionoscloud_dbaas_mongo/api/templates_api.py
ionoscloud_dbaas_mongo/api/users_api.py
ionoscloud_dbaas_mongo/models/__init__.py
ionoscloud_dbaas_mongo/models/api_version.py
ionoscloud_dbaas_mongo/models/cluster_list.py
ionoscloud_dbaas_mongo/models/cluster_list_all_of.py
ionoscloud_dbaas_mongo/models/cluster_logs.py
ionoscloud_dbaas_mongo/models/cluster_logs_instances.py
ionoscloud_dbaas_mongo/models/cluster_logs_messages.py
ionoscloud_dbaas_mongo/models/cluster_properties.py
ionoscloud_dbaas_mongo/models/cluster_response.py
ionoscloud_dbaas_mongo/models/connection.py
ionoscloud_dbaas_mongo/models/create_cluster_properties.py
ionoscloud_dbaas_mongo/models/create_cluster_request.py
ionoscloud_dbaas_mongo/models/create_restore_request.py
ionoscloud_dbaas_mongo/models/day_of_the_week.py
ionoscloud_dbaas_mongo/models/error_message.py
ionoscloud_dbaas_mongo/models/error_response.py
ionoscloud_dbaas_mongo/models/health.py
ionoscloud_dbaas_mongo/models/maintenance_window.py
ionoscloud_dbaas_mongo/models/metadata.py
ionoscloud_dbaas_mongo/models/pagination.py
ionoscloud_dbaas_mongo/models/pagination_links.py
ionoscloud_dbaas_mongo/models/patch_cluster_properties.py
ionoscloud_dbaas_mongo/models/patch_cluster_request.py
ionoscloud_dbaas_mongo/models/patch_user_properties.py
ionoscloud_dbaas_mongo/models/patch_user_request.py
ionoscloud_dbaas_mongo/models/resource_type.py
ionoscloud_dbaas_mongo/models/snapshot_list.py
ionoscloud_dbaas_mongo/models/snapshot_list_all_of.py
ionoscloud_dbaas_mongo-1.2.2.dist-info/LICENSE
ionoscloud_dbaas_mongo-1.2.2.dist-info/METADATA
ionoscloud_dbaas_mongo-1.2.2.dist-info/WHEEL
ionoscloud_dbaas_mongo-1.2.2.dist-info/top_level.txt
ionoscloud_dbaas_mongo-1.2.2.dist-info/RECORD
